pyfe/__init__.py
pyfe/context.py
pyfe/encrypted_vector.py
pyfe/encryptor.py
pyfe/key_generator.py
pyfe/master_key.py
pyfe/public_key.py
pyfe/utils.py
pyfe-0.0.1.dist-info/LICENSE
pyfe-0.0.1.dist-info/METADATA
pyfe-0.0.1.dist-info/WHEEL
pyfe-0.0.1.dist-info/top_level.txt
pyfe-0.0.1.dist-info/RECORD
